src/code_entry/CodeShiftRegister.v
module CodeShiftRegister(
    input  [3:0] digit,
    input        rst_n,      // active low
    input        shift,
    input        clk,
    output reg [15:0] code
);

    reg [1:0] segment;   // 0–3

    always @(posedge clk or negedge rst_n) begin
        if (!rst_n) begin
            code    <= 16'b0;
            segment <= 2'd0;
        end
        else if (shift) begin
            // Big endian nibble placement
            code[15 - segment*4 -: 4] <= digit;

            if (segment == 2'd3)
                segment <= 2'd0;
            else
                segment <= segment + 1;
        end
		  else begin 
			code[15 - segment*4 -: 4] <= digit;
		  end
    end

endmodule

src/code_entry/UpDownCounter.v
module UpDownCounterWrap(
	input wire clk,
	input wire rst_n,
	input wire ud,
	input wire trigger,
	output reg [3:0] count
);
	/*
		up down counter is a simple wrap around counter which
		on rising clock edge when a trigger is received we increment
		or decrement the count based on the input from ud representing up down
		

		min: 0
		max: 9
	*/

	always @(posedge clk or negedge rst_n) begin
		if (!rst_n) begin
			count <= 4'b0000;
		end
		else if (trigger) begin
			if (ud) begin
				if (count == 4'b1001)
					count <= 4'b0000;
				else
					count <= count + 1;
			end
			else begin
				if (count == 4'b0000)
					count <= 4'b1001;
				else
					count <= count - 1'b1;
			end
		end
	end
endmodule

src/code_entry/SinglePulse.v
module SinglePulse(
	input wire clk,
	input wire rst_n,
	input wire trigger,
	output reg pulse
);
	/*
		A one shot pulse which will fire a single pulse
		from the direction logic when trigger is received
	*/
	reg trigger_d;
	
	// delay input by one clock to detect rising edge
	always @(posedge clk or negedge rst_n) begin
		if (!rst_n)
			trigger_d <= 1'b0;
		else
			trigger_d <= trigger;
	end 
	
	// generate pulse on rising edge of trigger
	always @(posedge clk or negedge rst_n) begin
		if (!rst_n) begin
			pulse <= 1'b0;
		end
		else begin
			pulse <= trigger & ~trigger_d;
		end
	end
endmodule

src/code_entry/DirectionLogic.v
module DirectionLogic(
	input up,
	input down,
	output reg dir,
	output reg valid
);
	/* 
		Truth table which continuously outputs
		direction inputted from buttons for up/down
		counter as well as if the output is valid
	*/

	localparam DIR_UP = 1'b1;
	localparam DIR_DOWN = 1'b0;
	
	localparam IS_VALID = 1'b1;
	localparam NOT_VALID = 1'b0;
	
	always @(*) begin
		casex({up, down})
			2'b00: begin
				dir = 1'b0;
				valid = NOT_VALID;
			end
			2'b01: begin
				dir = DIR_DOWN;
				valid = IS_VALID;
			end
			2'b10: begin
				dir = DIR_UP;
				valid = IS_VALID;
			end
			2'b11: begin
				dir = 1'b0;
				valid = NOT_VALID;
			end
			default: begin
				dir = 1'b0;
				valid = NOT_VALID;
			end
		endcase
	end
endmodule

src/code_entry/ModeChangeDetector.v
module ModeChangeDetector(
	input clk,
	input rst_n,
	input [1:0] current_mode,
	output reg is_mode_change
);
	reg [1:0] previous_mode;
	
	always @(posedge clk or negedge rst_n) begin
		if (!rst_n) begin 
			previous_mode <= 2'b00;
			is_mode_change <= 1'b0;
		end
		else if (current_mode != previous_mode) begin
			previous_mode <= current_mode;
			is_mode_change <= 1'b1;
		end
		else begin
			is_mode_change <= 1'b0;
		end
	end
endmodule

src/code_entry/CodeEntry.v
// =========================
// Code Entry Sub Module
// =========================
/*
CodeEntry Module
Contains several sub modules: 
    - ModeChangeDetector
    - DirectionLogic
    - SinglePulse
    - UpDownCounterWrap
    - CodeShiftRegister

inputs: 
    - clk, rst_n, current_mode
    - keyb_s, keyc_s, keyd_s (up, down, shift buttons)

outputs: 
    - code: 16-bit code being entered
*/
module CodeEntry(
    input wire clk,
    input wire rst_n,
    input wire [1:0] current_mode, 
    input wire keyb_s,
    input wire keyc_s,
    input wire keyd_s,
    output wire [15:0] code
);
    /*
        top level of code entry module, 
        this module manages logic revolving around the code 
        entry for the digital system.
    */

    wire direction_logic_valid;
    wire direction_logic_dir;
    wire single_pulse_out;
    wire [3:0] counter_digit;
    wire mode_change_reset;
    wire rst_code_shift_register_inst_n = rst_n & !mode_change_reset;

    ModeChangeDetector mode_change_detector_inst(
        .clk(clk),
        .rst_n(rst_n), 
        .current_mode(current_mode),
        .is_mode_change(mode_change_reset)
    );
    DirectionLogic direction_logic_inst(
        .up(keyb_s),
        .down(keyc_s),
        .dir(direction_logic_dir),
        .valid(direction_logic_valid)
    );
    SinglePulse single_pulse_inst(
        .clk(clk),
        .rst_n(rst_n),
        .trigger(direction_logic_valid),
        .pulse(single_pulse_out)
    );
    UpDownCounterWrap up_down_counter_inst(
        .clk(clk),
        .rst_n(rst_n),
        .ud(direction_logic_dir),
        .trigger(single_pulse_out),
        .count(counter_digit)
    );
    CodeShiftRegister code_shift_register_inst(
        .digit(counter_digit),
        .rst_n(rst_code_shift_register_inst_n),
        .shift(keyd_s),
        .clk(clk),
        .code(code)
    );
endmodule

tests/test_code_entry/CodeEntry_tb.v
`timescale 1ns/1ps

module CodeEntry_tb;

    // =========================
    // Testbench Signals
    // =========================
    reg clk;
    reg rst_n;
    reg [1:0] current_mode;
    reg keyb_s;
    reg keyc_s;
    reg keyd_s;

    wire [15:0] code;

    // =========================
    // DUT Instantiation
    // =========================
    CodeEntry DUT (
        .clk(clk),
        .rst_n(rst_n),
        .current_mode(current_mode),
        .keyb_s(keyb_s),
        .keyc_s(keyc_s),
        .keyd_s(keyd_s),
        .code(code)
    );

    // =========================
    // Clock Generation
    // =========================
    initial begin
        clk = 0;
        forever #10 clk = ~clk;   // 20ns clock period
    end

    // =========================
    // Waveform Dump (for GTKWave)
    // =========================
    initial begin
        $dumpfile("CodeEntry_tb.vcd");
        $dumpvars(0, CodeEntry_tb);
    end

    // =========================
    // Monitor
    // =========================
    initial begin
        $monitor("T=%0t | rst_n=%b | mode=%b | B=%b C=%b D=%b | code=%h",
                  $time, rst_n, current_mode, keyb_s, keyc_s, keyd_s, code);
    end

    // =========================
    // Test Stimulus
    // =========================
    initial begin

        // -------------------------
        // Initial Conditions
        // -------------------------
        rst_n        = 0;
        current_mode = 2'b00;
        keyb_s       = 0;
        keyc_s       = 0;
        keyd_s       = 0;

        // Release reset
        #25;
        rst_n = 1;

        // =====================================================
        // TEST 1: keyb high → increment digit
        // =====================================================
        #20;
        keyb_s = 1;
        @(posedge clk);
		  #20
        keyb_s = 0;
        @(posedge clk);

        // =====================================================
        // TEST 2: keyc high → decrement digit
        // =====================================================
        #20;
        keyc_s = 1;
        @(posedge clk);
		  #20
        keyc_s = 0;
        @(posedge clk);

        // =====================================================
        // TEST 3: keyb and keyc high together → invalid
        // Code should not change
        // =====================================================
        #20;
        keyb_s = 1;
        keyc_s = 1;
        @(posedge clk);
		  #20
        keyb_s = 0;
        keyc_s = 0;
        @(posedge clk);

        // =====================================================
        // TEST 4: Shift operation
        // 1) Increment
        // 2) Shift
        // 3) Increment again
        // =====================================================
        #20;

        // Increment current digit
        keyb_s = 1;
        @(posedge clk);
			#20; 
			keyb_s = 0;
		
        // Shift
        keyd_s = 1;
        @(posedge clk);
        keyd_s = 0;

        // Increment new digit
        keyb_s = 1;
        @(posedge clk);
        keyb_s = 0;
        @(posedge clk);

        // =====================================================
        // TEST 5: Mode change reset
        // =====================================================
        #20;
        current_mode = 2'b01;   // simulate mode change
        @(posedge clk);

		  #20;
		  keyc_s = 1'b1;
		  @(posedge clk);
		  keyc_s = 1'b1;
		  @(posedge clk);
		  
        // =====================================================
        // TEST 6: Global reset
        // =====================================================
        #20;
        rst_n = 0;
        @(posedge clk);
		  #10;
        rst_n = 1;
        @(posedge clk);

        // Let simulation run a little longer
        #50;

        $finish;
    end

endmodule

src/simulation/modelsim/CodeEntry_tb.vcd
$date
	Wed Feb 11 20:26:01 2026
$end
$version
	ModelSim Version 10.1d
$end
$timescale
	1ps
$end
$scope module CodeEntry_tb $end
$var reg 1 ! clk $end
$var reg 1 " rst_n $end
$var reg 2 # current_mode [1:0] $end
$var reg 1 $ keyb_s $end
$var reg 1 % keyc_s $end
$var reg 1 & keyd_s $end
$var wire 1 ' code [15] $end
$var wire 1 ( code [14] $end
$var wire 1 ) code [13] $end
$var wire 1 * code [12] $end
$var wire 1 + code [11] $end
$var wire 1 , code [10] $end
$var wire 1 - code [9] $end
$var wire 1 . code [8] $end
$var wire 1 / code [7] $end
$var wire 1 0 code [6] $end
$var wire 1 1 code [5] $end
$var wire 1 2 code [4] $end
$var wire 1 3 code [3] $end
$var wire 1 4 code [2] $end
$var wire 1 5 code [1] $end
$var wire 1 6 code [0] $end
$scope module DUT $end
$var wire 1 7 clk $end
$var wire 1 8 rst_n $end
$var wire 1 9 current_mode [1] $end
$var wire 1 : current_mode [0] $end
$var wire 1 ; keyb_s $end
$var wire 1 < keyc_s $end
$var wire 1 = keyd_s $end
$var wire 1 ' code [15] $end
$var wire 1 ( code [14] $end
$var wire 1 ) code [13] $end
$var wire 1 * code [12] $end
$var wire 1 + code [11] $end
$var wire 1 , code [10] $end
$var wire 1 - code [9] $end
$var wire 1 . code [8] $end
$var wire 1 / code [7] $end
$var wire 1 0 code [6] $end
$var wire 1 1 code [5] $end
$var wire 1 2 code [4] $end
$var wire 1 3 code [3] $end
$var wire 1 4 code [2] $end
$var wire 1 5 code [1] $end
$var wire 1 6 code [0] $end
$var wire 1 > direction_logic_valid $end
$var wire 1 ? direction_logic_dir $end
$var wire 1 @ single_pulse_out $end
$var wire 1 A counter_digit [3] $end
$var wire 1 B counter_digit [2] $end
$var wire 1 C counter_digit [1] $end
$var wire 1 D counter_digit [0] $end
$var wire 1 E mode_change_reset $end
$var wire 1 F rst_code_shift_register_inst_n $end
$scope module mode_change_detector_inst $end
$var wire 1 7 clk $end
$var wire 1 8 rst_n $end
$var wire 1 9 current_mode [1] $end
$var wire 1 : current_mode [0] $end
$var reg 1 G is_mode_change $end
$var reg 2 H previous_mode [1:0] $end
$upscope $end
$scope module direction_logic_inst $end
$var parameter 1 I DIR_UP $end
$var parameter 1 J DIR_DOWN $end
$var parameter 1 K IS_VALID $end
$var parameter 1 L NOT_VALID $end
$var wire 1 ; up $end
$var wire 1 < down $end
$var reg 1 M dir $end
$var reg 1 N valid $end
$upscope $end
$scope module single_pulse_inst $end
$var wire 1 7 clk $end
$var wire 1 8 rst_n $end
$var wire 1 > trigger $end
$var reg 1 O pulse $end
$var reg 1 P trigger_d $end
$upscope $end
$scope module up_down_counter_inst $end
$var wire 1 7 clk $end
$var wire 1 8 rst_n $end
$var wire 1 ? ud $end
$var wire 1 @ trigger $end
$var reg 4 Q count [3:0] $end
$upscope $end
$scope module code_shift_register_inst $end
$var wire 1 A digit [3] $end
$var wire 1 B digit [2] $end
$var wire 1 C digit [1] $end
$var wire 1 D digit [0] $end
$var wire 1 F rst_n $end
$var wire 1 = shift $end
$var wire 1 7 clk $end
$var reg 16 R code [15:0] $end
$var reg 2 S segment [1:0] $end
$upscope $end
$upscope $end
$upscope $end
$enddefinitions $end
#0
$dumpvars
0!
0"
b0 #
0$
0%
0&
0G
b0 H
0M
0N
0O
0P
b0 Q
b0 R
b0 S
b1 I
b0 J
b1 K
b0 L
06
05
04
03
02
01
00
0/
0.
0-
0,
0+
0*
0)
0(
0'
0>
0?
0@
0D
0C
0B
0A
0E
0F
0=
0<
0;
0:
09
08
07
$end
#10000
1!
17
#20000
0!
07
#25000
1"
18
1F
#30000
1!
17
#40000
0!
07
#45000
1$
1;
1M
1N
1?
1>
#50000
1!
17
1P
1O
1@
#60000
0!
07
#70000
0$
1!
0;
17
0M
0N
0?
0>
0O
b1 Q
0@
1D
#80000
0!
07
#90000
1%
1!
1<
17
1N
1>
0P
b1000000000000 R
1*
#100000
0!
07
#110000
0%
1!
0<
17
0N
0>
1P
1O
1@
#120000
0!
07
#130000
1$
1%
1!
1;
1<
17
0P
0O
b0 Q
0@
0D
#140000
0!
07
#150000
0$
0%
1!
0;
0<
17
b0 R
0*
#160000
0!
07
#170000
1$
1!
1;
17
1M
1N
1?
1>
#180000
0!
07
#190000
0$
1&
1!
1=
0;
17
0M
0N
0&
1$
0?
0>
0=
1;
1M
1N
1?
1>
1P
1O
b1 S
1@
#200000
0!
07
#210000
1!
17
0$
0;
0M
0N
0?
0>
0O
b1 Q
0@
1D
#220000
0!
07
#230000
1!
17
0P
b100000000 R
1.
#240000
0!
07
#250000
b1 #
1!
1:
17
b1 H
1G
1E
0F
b0 R
b0 S
0.
#260000
0!
07
#270000
1%
1!
1<
17
1N
1>
0G
0E
1F
#280000
0!
07
#290000
1!
17
1P
1O
b1000000000000 R
1@
1*
#300000
0!
07
#310000
0"
1!
08
17
0F
b0 R
b0 H
0P
0O
b0 Q
0@
0D
0*
#320000
0!
1"
07
18
1F
#330000
1!
17
b1 H
1G
1P
1O
1E
1@
0F
#340000
0!
07
#350000
1!
17
0G
0O
b1001 Q
0E
0@
1D
1A
1F
#360000
0!
07
#370000
1!
17
b1001000000000000 R
1*
1'
